torchneuro/__init__.py
torchneuro-0.0.dist-info/LICENSE
torchneuro-0.0.dist-info/METADATA
torchneuro-0.0.dist-info/WHEEL
torchneuro-0.0.dist-info/RECORD
