Metadata-Version: 2.1
Name: torchneuro
Version: 0.0
Summary: 
Author: Will Brennan
Author-email: WillBrennan@users.noreply.github.com
Requires-Python: >=3.8,<4.0
Classifier: Programming Language :: Python :: 3
Classifier: Programming Language :: Python :: 3.8
Classifier: Programming Language :: Python :: 3.9
Classifier: Programming Language :: Python :: 3.10
Classifier: Programming Language :: Python :: 3.11
